[
    {
        "created": "20201217042528647",
        "title": "Riedran Sea",
        "text": "Over centuries, the [[Inspired]] have built a network of monoliths\nin [[Riedra]], psychic anchors called [[hanbalani alta]]s. These allow\nthem to control everyone's dreams over a vast radius. Dreams\nare typically tailored to the region, including local news and\ninstructions. However, if they choose, the Inspired can broadcast\na single dream to all of [[Sarlona]]. Within [[Dal Quor]], this manifests as a distinctive region of the [[Ocean of Dreams]]—an array of\nhundreds of thousands of islands, dream-bubbles arranged in\nperfect symmetrical rows, with identical images in each bubble.",
        "modified": "20210727192028316",
        "tags": "[[Dal Quor]] layer",
        "type": "text/vnd.tiddlywiki",
        "article": "the ",
        "category": "location",
        "color": "#3B5C0A"
    }
]