[
    {
        "created": "20220130203709881",
        "text": "In the eastern quadrant of [[Fairhaven]], the [[Sovereign Host]] has a\nsprawling temple in the ward to which it lends its\nname. The temple has a central ''Hall of the Assembled Host'' that seats almost six thousand worshipers. Individual shrines to each of the deities that comprise the\nSovereign Host surround the central hall; [[Arawai]]\nand [[Olladra]]’s shrines are particularly large and well-attended. The surrounding buildings provide residences for the acolytes and priests of the temple. In the south part of the ward, a number of vacant buildings emphasize the crumbling emptiness of the abandoned Church of the [[Silver Flame]], [[Old Tira's Mercy]].\n\n!! Noteworthy Locations\n\n* ''Hall of the Assembled Host'' (temple to the [[Sovereign Host]])\n* ''Saint's Hall'' (inn)\n* ''Haldran Books'' (shop)\n* [[ir'Uvanto Family Antiquities]]\n* [[Old Tira's Mercy]]",
        "type": "text/vnd.tiddlywiki",
        "title": "Sovereign Ward",
        "tags": "district Fairhaven",
        "modified": "20230901200613342",
        "style": "{\"color\":\"#6B001B\",\"fillColor\":\"#8E0024\",\"fillOpacity\":0.3}",
        "polygons": "47.671,-9.874 47.658,-9.874 47.639,-9.847 47.65,-9.834 47.65,-9.829 47.654,-9.824 47.654,-9.818 47.657,-9.818 47.657,-9.814 47.66,-9.81 47.678,-9.81 47.68,-9.814 47.68,-9.818 47.694,-9.818 47.702,-9.829",
        "color": "#96CC39",
        "category": "location",
        "article": "the "
    }
]