[
    {
        "created": "20210222212354109",
        "text": "The Titan's Teeth in [[Xen'drik]] form the southern boundary of the [[Skyfall Peninsula]]. A band of [[frost giant]]s dwell in a hidden valley high in these mountains known as Icefang Vale. These mountains are also home to a unique variety of avian humanoids known as \"raptorans\" to those of [[Stormreach]].",
        "title": "Titan's Teeth",
        "modified": "20221205075635692",
        "tags": "Xen'drik mountains",
        "type": "text/vnd.tiddlywiki",
        "article": "the ",
        "category": "location",
        "color": "#3B5C0A",
        "polygons": "-18.12,-42.02 -17.132,-41.67 -15.849,-40.82 -15.185,-40.27 -15.24,-39.28 -15.065,-38.54 -15.618,-37.58 -16.025,-36.39 -16.726,-36.25 -17.169,-36.89 -17.723,-37.56 -18.443,-38.32 -18.757,-39.78 -18.378,-40.75 -19.052,-41.51 -18.877,-42.03",
        "style": "{\"color\":\"#4D382C\",\"fillColor\":\"#6B5334\",\"fillOpacity\":\"0.5\"}"
    }
]