[
    {
        "created": "20210126011634312",
        "text": "The Unity forms the foundation of [[Riedra]]n government, and the\nmajority of the population serves one of its branches.\nWhile each branch of the Unity has its own ministers,\nthe seven arms work together in the service of the nation\nand answer to the local [[bastion|bastion city]] lords. This arrangement\nseparates the Unity from the [[Thousand Eyes]] and [[Harmonious Shield]], which follow different chains of command.\nAll branch high ministers are skilled [[psion]]s.\n\n!! Branches of the Unity of Riedra\n\n<<list-links-article \"[tag{!!title}sort[title]]\">>",
        "title": "Unity",
        "modified": "20221215215855182",
        "tags": "government Riedra",
        "type": "text/vnd.tiddlywiki",
        "article": "the ",
        "category": "organization",
        "color": "#9EC5FE",
        "tooltip": "central government of Riedra"
    }
]